CHANGES.txt
MANIFEST.in
README.md
info.py
japanese_holiday.py
requirements.txt
setup.py
version.py
japanese_holiday.egg-info/PKG-INFO
japanese_holiday.egg-info/SOURCES.txt
japanese_holiday.egg-info/dependency_links.txt
japanese_holiday.egg-info/entry_points.txt
japanese_holiday.egg-info/requires.txt
japanese_holiday.egg-info/top_level.txt