Metadata-Version: 1.1
Name: japanese-holiday
Version: 0.0.4
Summary: Get Japanese holiday lib.
Home-page: https://bitbucket.org/vourja/japanese-holiday
Author: J Yukawa
Author-email: j.yukawa@gmail.com
License: MIT
Keywords: japanese holiday
Platform: UNKNOWN
Classifier: Development Status :: 1 - Planning
Classifier: Intended Audience :: Developers
Classifier: Programming Language :: Python
Classifier: Programming Language :: Python :: 2.7
Classifier: License :: OSI Approved :: MIT License
